{
  "timestamp" : "2022-12-25T00:43:28Z",
  "count_outdated" : 2675,
  "uniques_outdated" : 734,
  "count" : 2687,
  "uniques" : 739,
  "clones" : [
    {
      "timestamp": "2022-12-11T00:00:00Z",
      "count": 7,
      "count_minmax": [ 6, 7 ],
      "count_decinc": [ 0, 7 ],
      "uniques": 3,
      "uniques_minmax": [ 2, 3 ],
      "uniques_decinc": [ 0, 3 ]
    },
    {
      "timestamp": "2022-12-18T00:00:00Z",
      "count": 4,
      "count_minmax": [ 4, 4 ],
      "count_decinc": [ 0, 4 ],
      "uniques": 1,
      "uniques_minmax": [ 1, 1 ],
      "uniques_decinc": [ 0, 1 ]
    },
    {
      "timestamp": "2022-12-24T00:00:00Z",
      "count": 1,
      "count_minmax": [ 1, 1 ],
      "count_decinc": [ 0, 1 ],
      "uniques": 1,
      "uniques_minmax": [ 1, 1 ],
      "uniques_decinc": [ 0, 1 ]
    }
  ]
}
